biorxiv_server.py
biorxiv_web_search.py
iflow_mcp_biorxiv_mcp_server-0.1.0.dist-info/METADATA
iflow_mcp_biorxiv_mcp_server-0.1.0.dist-info/WHEEL
iflow_mcp_biorxiv_mcp_server-0.1.0.dist-info/entry_points.txt
iflow_mcp_biorxiv_mcp_server-0.1.0.dist-info/top_level.txt
iflow_mcp_biorxiv_mcp_server-0.1.0.dist-info/RECORD
