Metadata-Version: 2.4
Name: iflow-mcp_biorxiv-mcp-server
Version: 0.1.0
Summary: An MCP server for searching and retrieving articles from bioRxiv
Requires-Python: >=3.10
Requires-Dist: mcp[cli]>=1.4.1
Requires-Dist: requests>=2.25.1
Requires-Dist: beautifulsoup4>=4.9.3
